[
  {
	"event": [
	  { "action": "set_background", "target": "town_medical_tent" },
	  { "action": "show_talk_ui" }
	],
	"text": "The street-side medical stall smelled faintly of herbs. The white cloth curtain swayed gently in the breeze."
  },
  {
	"event": { "action": "show_name", "target": "Alicia" },
	"text": "“Here.”"
  },
  {
	"text": "Alicia guided me to sit down. “Let them change your bandages properly.”"
  },
  {
	"event": { "action": "show_name", "target": "Player" },
	"text": "“That’s not necessary. I think it’s fine now.”"
  },
  {
	"event": { "action": "show_name", "target": "Alicia" },
	"text": "She raised an eyebrow. “You almost left your arm in that forest this morning.”"
  },
  {
	"text": "The apothecary brought clean bandages and a bowl of rinse water. Alicia took them herself, deftly unwrapping the old cloth and replacing it layer by layer."
  },
  {
	"event": { "action": "show_name", "target": "Player" },
	"text": "“You’ve done this before?”"
  },
  {
	"event": { "action": "show_name", "target": "Alicia" },
	"text": "“When you’re a mercenary, not knowing how to treat a wound is as good as signing your death warrant.”"
  },
  {
	"text": "Her tone was calm. The last strip of bandage was tied into a neat knot."
  },
  {
	"text": "Her hand lingered on mine for a moment, as if checking that the pulse beneath the skin had steadied."
  },
  {
	"event": { "action": "show_name", "target": "Alicia" },
	"text": "“Still hurt?”"
  },
  {
	"event": { "action": "show_name", "target": "Player" },
	"text": "“Not anymore. Your hands work better than the medicine.”"
  },
  {
	"text": "She paused, then gave a small laugh. Sunlight slipped through the curtain, flickering over her eyelashes."
  },
  {
	"text": "Then, she took my hand in hers."
  },
  {
	"text": "For a moment, the noise of the marketplace faded, leaving only the warmth of her touch."
  },
  {
	"event": [{ "action": "change_scene", "target": "scene1.6" }]
  }
]
